PaasSdk/Config.py
PaasSdk/CreateRequestClient.py
PaasSdk/DeveloperCenterConfig.py
PaasSdk/PaasSendExampleApi.py
PaasSdk/RequestModel.py
PaasSdk/ResponseModel.py
PaasSdk/RonyingCommon.py
PaasSdk/__init__.py
RongyingPaasSdk-1.1.5.dist-info/METADATA
RongyingPaasSdk-1.1.5.dist-info/WHEEL
RongyingPaasSdk-1.1.5.dist-info/top_level.txt
RongyingPaasSdk-1.1.5.dist-info/RECORD
