Metadata-Version: 2.1
Name: RongyingPaasSdk
Version: 1.1.5
Summary: rongyingyun  Paas SDK Library for Python
Home-page: https://gitee.com/ccgkxdy/paas-sdk-python
Author: rongyingyun Paas SDK
Author-email: xdy@cyjcloud.com
License: Apache License 2.0
Keywords: rongyingyun,RongyingPaasSdk
Platform: any
Classifier: Development Status :: 4 - Beta
Classifier: Intended Audience :: Developers
Classifier: License :: OSI Approved :: Apache Software License
Classifier: Programming Language :: Python
Classifier: Programming Language :: Python :: 3
Classifier: Programming Language :: Python :: 3.6
Classifier: Programming Language :: Python :: 3.7
Classifier: Programming Language :: Python :: 3.8
Classifier: Programming Language :: Python :: 3.9
Classifier: Topic :: Software Development
Requires-Python: >=3
Requires-Dist: requests
